_lycon2.so
lycon2-0.3.4.dist-info/zip-safe
lycon2-0.3.4.dist-info/WHEEL
lycon2-0.3.4.dist-info/top_level.txt
lycon2-0.3.4.dist-info/LICENSE
lycon2-0.3.4.dist-info/RECORD
lycon2-0.3.4.dist-info/METADATA
lycon2/__init__.py
lycon2/enum.py
lycon2/core.py
lycon2.libs/libpng12-640ca796.so.0.49.0
lycon2.libs/libjpeg-7feae879.so.62.0.0
